uclcoin/__init__.py
uclcoin/block.py
uclcoin/blockchain.py
uclcoin/exceptions.py
uclcoin/keypair.py
uclcoin/transaction.py
uclcoin-0.3.2.dist-info/METADATA
uclcoin-0.3.2.dist-info/RECORD
uclcoin-0.3.2.dist-info/WHEEL
uclcoin-0.3.2.dist-info/top_level.txt
