Metadata-Version: 2.1
Name: uclcoin
Version: 0.3.2
Summary: UCLCoin: A naive blockchain/cryptocurrency implementation
Home-page: https://github.com/orgito/uclcoin
Author: Renato Orgito
Author-email: orgito@gmail.com
Maintainer: Renato Orgito
Maintainer-email: orgito@gmail.com
License: MIT
Project-URL: Bug Reports, https://github.com/orgito/uclcoin/issues
Project-URL: Source, https://github.com/orgito/uclcoin
Keywords: uclcoin blockchain cryptocurrency
Platform: UNKNOWN
Classifier: Development Status :: 3 - Alpha
Classifier: Intended Audience :: Education
Classifier: Intended Audience :: Science/Research
Classifier: Topic :: Education
Classifier: Topic :: Security :: Cryptography
Classifier: License :: OSI Approved :: MIT License
Classifier: Operating System :: OS Independent
Classifier: Programming Language :: Python :: 3.6
Requires-Python: >=3.6
Requires-Dist: coincurve
Requires-Dist: pymongo
